currency_to_words/__init__.py
currency_to_words-0.1.1.dist-info/LICENSE
currency_to_words-0.1.1.dist-info/METADATA
currency_to_words-0.1.1.dist-info/WHEEL
currency_to_words-0.1.1.dist-info/top_level.txt
currency_to_words-0.1.1.dist-info/RECORD
