Metadata-Version: 2.2
Name: currency_to_words
Version: 0.1.1
Summary: A library to convert currency to words in Indian numbering system
Home-page: https://github.com/Madhan-raio-97/currency_to_words
Author: Madhanagopal Mallayan
Author-email: madhanagopalpro@gmail.com
License: MIT
Classifier: Programming Language :: Python :: 3
Classifier: License :: OSI Approved :: MIT License
Classifier: Operating System :: OS Independent
Requires-Python: >=3.6
License-File: LICENSE
Dynamic: author
Dynamic: author-email
Dynamic: classifier
Dynamic: description
Dynamic: description-content-type
Dynamic: home-page
Dynamic: license
Dynamic: requires-python
Dynamic: summary
